# ğŸ“– ìë°” ë¬¸ìì—´

# í•™ìŠµ ëª©í‘œ

- ë¬¸ì(char, Character)ì™€ ë¬¸ìì—´(String)
- StringBuilderì™€ StringBuffer

## ë¬¸ìì™€ ë¬¸ìì—´

- ë¬¸ìì—´(String)ì€ ìë°” í”„ë¡œê·¸ë¨ì´ ì‹¤í–‰ë˜ëŠ” ë™ì•ˆ ê°€ì¥ ë§ì´ ìƒì„±ë˜ëŠ” ê°ì²´ì´ë‹¤.
- ë¬¸ìì—´ì€ ê°ì²´ì´ì§€ë§Œ ê°ê°ì˜ ë¬¸ìì˜ ë‚˜ì—´ë¡œ êµ¬ì„±ëœë‹¤.
- ë¬¸ìì—´ì€ StringPoolì—ì„œ ê´€ë¦¬í•œë‹¤.
- char capitalA = â€˜Aâ€™; // ë¬¸ì
- String a = â€œabcâ€; // ë¬¸ìì—´ == ë¬¸ìì˜ ë°°ì—´
- String b = new String(â€œabcâ€); // ì´ì™€ ê°™ì´ êµ¬í˜„í•˜ì§€ ë§ˆë¼.

## new String() êµ¬í˜„ì‹œ ì°¨ì´

#### êµ¬í˜„ ì½”ë“œ

```java
public void testString() throws Exception {
    String a = "abc";
}

public void testNewString() throws Exception {
    String b = new String("abc");
}
```

#### ì»´íŒŒì¼ëœ class ì½”ë“œ

```java
 public void testString() throws java.lang.Exception;
    Code:
       0: ldc           #89                 // String abc
       2: astore_1
       3: return

  public void testNewString() throws java.lang.Exception;
    Code:
       0: new           #33                 // class java/lang/String
       3: dup
       4: ldc           #89                 // String abc
       6: invokespecial #93   // Method java/lang/String."<init>":(Ljava/lang/String;)V
       9: astore_1
      10: return
```

ë¬¸ìì—´(String)ì€ ìë°” í”„ë¡œê·¸ë¨ì´ ì‹¤í–‰ë˜ëŠ” ë™ì•ˆ **ê°€ì¥ ë§ì´ ìƒì„±ë˜ëŠ” ê°ì²´**ì´ë‹¤.
ë¬¸ìì—´ì€ ê°ì²´ì´ì§€ë§Œ ê°ê°ì˜ **ë¬¸ìì˜ ë‚˜ì—´**ë¡œ êµ¬ì„±ëœë‹¤.

## String APIì— ëŒ€í•œ í•™ìŠµ í…ŒìŠ¤íŠ¸

```java
import org.junit.Test;

import static org.assertj.core.api.Assertions.assertThat;

public class StringTest {
    @Test
    public void ë¬¸ìì—´_ê¸¸ì´_êµ¬í•˜ê¸°() throws Exception {
        String name = "ë°•ì¬ì„±";
        assertThat([TODO ê¸¸ì´ êµ¬í•˜ê¸°]).isEqualTo(3);
    }

    @Test
    public void ë¬¸ìì—´_ë”í•˜ê¸°() throws Exception {
        String name = "ë°•ì¬ì„±";
        String welcome = "ì•ˆë…•!";
        assertThat([TODO ë¬¸ìì—´ ë”í•˜ê¸°]).isEqualTo("ì•ˆë…•!ë°•ì¬ì„±");
    }

    @Test
    public void ë¬¸ìì—´ì„_ë¬¸ì_ë‹¨ìœ„ë¡œ_ì¶œë ¥() throws Exception {
        String name = "ë°•ì¬ì„±";
        // Stringì˜ ê° ë¬¸ìë¥¼ ë°°ì—´ë¡œ ê°€ì ¸ì˜¬ ìˆ˜ ìˆëŠ” API í™œìš©í•´ êµ¬í˜„ ê°€ëŠ¥
        [TODO ë¬¸ìì—´ ì¶œë ¥]
    }

    @Test
    public void ë¬¸ìì—´_ë’¤ì§‘ê¸°() throws Exception {
        String name = "ë°•ì¬ì„±";

        // Stringì˜ ê° ë¬¸ìë¥¼ ë°°ì—´ë¡œ ê°€ì ¸ì˜¬ ìˆ˜ ìˆëŠ” API í™œìš©í•´ êµ¬í˜„ ê°€ëŠ¥
        [TODO ë¬¸ìì—´ ë’¤ì§‘ê¸°]

        assertThat(reverseName).isEqualTo("ì„±ì¬ë°•");
    }
}
```

## StringBuilder API

#### String + String vs StringBuilder

- Stringì€ ë¶ˆë³€í•˜ê¸°(immutable)ì´ê¸° ë•Œë¬¸ì— Stringê³¼ Stringì„ ë”í•˜ë©´ ìƒˆë¡œìš´ String ê°ì²´ë¥¼ ìƒì„±í•œë‹¤. ë”°ë¼ì„œ Stringê³¼ Stringì„ ë”í•˜ëŠ” ì‹œì ì— ë©”ëª¨ë¦¬ í• ë‹¹ê³¼ ë©”ëª¨ë¦¬ í•´ì œê°€ ê³„ì† ë°œìƒí•œë‹¤.
- StringBuilderëŠ” Stringê³¼ ë‹¤ë¥´ê²Œ ê¸°ì¡´ ë°ì´í„°ì— ìƒˆë¡œìš´ ë°ì´í„°ë¥¼ ë”í•˜ëŠ” ë°©ì‹ì„ ì·¨í•˜ê¸° ë•Œë¬¸ì— ì†ë„ê°€ ë” ë¹ ë¥´ë‹¤.
- ë”°ë¼ì„œ ê¸´ ë¬¸ìì—´ì„ ë”í•˜ëŠ” ìƒí™©ì´ ë°œìƒí•˜ëŠ” ê²½ìš° StringBuilderë¥¼ í™œìš©í•´ êµ¬í˜„í•œë‹¤.

#### immutable

- Immutable(ë¶ˆë³€)ì´ë€ ê°ì²´ë¥¼ ìƒì„±í•œ í›„ ìƒíƒœë¥¼ ë³€ê²½í•  ìˆ˜ ì—†ëŠ” ê²ƒì„ ì˜ë¯¸í•œë‹¤.
- String ê°ì²´ëŠ” ë¬¸ìì—´ì˜ ìƒíƒœ ê°’ì„ ë³€ê²½í•  ìˆ˜ ì—†ê¸° ë•Œë¬¸ì— immutable ê°ì²´ë¼ í•œë‹¤.

#### StringBuilder API í•™ìŠµ í…ŒìŠ¤íŠ¸

- StringBuilderë¥¼ í™œìš©í•´ ìê¸°ì†Œê°œ ë¬¸ì ì¶œë ¥í•œë‹¤.
- ë¬¸ìì—´ì„ ë”í•  ë•Œ ë”í•˜ê¸°(+) ì—°ì‚°ìë¥¼ ì‚¬ìš©í•˜ì§€ ì•Šì•„ì•¼ í•œë‹¤.

```java
import org.junit.Test;

import static org.assertj.core.api.Assertions.assertThat;

public class StringBuilderTest {
    @Test
    public void append () {
        assertThat(createMessage("ë°•ì¬ì„±")).isEqualTo("ì•ˆë…•í•˜ì„¸ìš”, ì €ëŠ” ë°•ì¬ì„±ì…ë‹ˆë‹¤.");
    }

    private String createMessage(String name) {
        StringBuilder sb = new StringBuilder();
        // TODO append() ë©”ì†Œë“œ í™œìš©í•´ ìš”êµ¬ì‚¬í•­ êµ¬í˜„
        return sb.toString();
    }
}
```

- StringBuilderë¥¼ ì‚¬ìš©í•˜ëŠ” ê²½ìš° + ì—°ì‚°ì„ í†µí•´ ë¬¸ìì—´ì„ ìƒì„±í•˜ì§€ ì•Šê³  appendë¥¼ í™œìš©í•´ì•¼ í•œë‹¤.